README.md
setup.py
LineService/__init__.py
LineService/constants.py
LineService/f_AccountSupervisorService.py
LineService/f_AgeCheckService.py
LineService/f_AuthService.py
LineService/f_BotService.py
LineService/f_BuddyManagementService.py
LineService/f_BuddyService.py
LineService/f_CallService.py
LineService/f_ChannelApplicationProvidedService.py
LineService/f_ChannelService.py
LineService/f_MessageService.py
LineService/f_ShopService.py
LineService/f_SnsAdaptorService.py
LineService/f_SpotService.py
LineService/f_SquareService.py
LineService/f_TalkService.py
LineService/f_UniversalNotificationService.py
LineService/ttypes.py
LineService.egg-info/PKG-INFO
LineService.egg-info/SOURCES.txt
LineService.egg-info/dependency_links.txt
LineService.egg-info/requires.txt
LineService.egg-info/top_level.txt