Metadata-Version: 2.1
Name: LineService
Version: 0.10.1
Summary: Line Messaging protocol for Python
Home-page: https://github.com/dyseo/LineService
Author: Dyseo
Author-email: katro.coplax@gmail.com
License: UNKNOWN
Keywords: frugal thrift line lineservice
Platform: UNKNOWN
Classifier: Programming Language :: Python
Classifier: Programming Language :: Python :: 2.7
Classifier: Programming Language :: Python :: 3.5
Classifier: Programming Language :: Python :: 3.6
Classifier: Programming Language :: Python :: 3.7
Classifier: Topic :: Software Development :: Libraries :: Python Modules
